minecode/__init__.py
minecode/server.py
minecode/config/config.json
minecode/config/prompt_config.json
minecode/preprompts/assistant_preprompt.txt
minecode/scrappers/__init__.py
minecode/scrappers/minecraftwiki.py
minecode/scrappers/misode.py
minecode/scrappers/mojira.py
minecode/scrappers/spyglass.py
minecode_mcp-0.1.6.dist-info/METADATA
minecode_mcp-0.1.6.dist-info/WHEEL
minecode_mcp-0.1.6.dist-info/entry_points.txt
minecode_mcp-0.1.6.dist-info/licenses/LICENSE
minecode_mcp-0.1.6.dist-info/RECORD
