Metadata-Version: 2.4
Name: minecode-mcp
Version: 0.1.6
Summary: MCP Server for Minecraft datapack development with wiki, Spyglass, Misode, and Mojira integrations
Project-URL: Homepage, https://github.com/AnCarsenat/minecode-mcp
Project-URL: Repository, https://github.com/AnCarsenat/minecode-mcp
Project-URL: Issues, https://github.com/AnCarsenat/minecode-mcp/issues
Author-email: Ancarsenat <antoine.carsenat@example.com>
License-Expression: MIT
License-File: LICENSE
Keywords: ai,copilot,datapack,mcp,minecraft
Classifier: Development Status :: 4 - Beta
Classifier: Intended Audience :: Developers
Classifier: License :: OSI Approved :: MIT License
Classifier: Programming Language :: Python :: 3
Classifier: Programming Language :: Python :: 3.10
Classifier: Programming Language :: Python :: 3.11
Classifier: Programming Language :: Python :: 3.12
Classifier: Topic :: Games/Entertainment
Requires-Python: >=3.10
Requires-Dist: beautifulsoup4>=4.12.0
Requires-Dist: mcp>=1.25.0
Requires-Dist: requests>=2.31.0
